<image number="9">
<img index="0" file="c:\tangramvect\bigtriangle1.jpg"></img>
<img index="1" file="c:\tangramvect\bigtriangle2.jpg"></img>
<img index="2" file="c:\tangramvect\midtriangle.jpg"></img>
<img index="3" file="c:\tangramvect\smalltriangle1.jpg"></img>
<img index="4" file="c:\tangramvect\smalltriangle2.jpg"></img>
<img index="5" file="c:\tangramvect\rect.jpg"></img>
<img index="6" file="c:\tangramvect\square.jpg"></img>
<img index="7" file="c:\tangramvect\active.jpg"></img>
<img index="8" file="c:\tangramvect\focus.jpg"></img>
</image>
